agbpycc/__init__.py
agbpycc/__main__.py
agbpycc/ast.py
agbpycc/parse_debug.py
agbpycc/parser.py
agbpycc/antlr/ASMLexer.py
agbpycc/antlr/ASMListener.py
agbpycc/antlr/ASMParser.py
agbpycc/antlr/ASMVisitor.py
agbpycc/antlr/__init__.py
agbpycc-0.2.0.dist-info/METADATA
agbpycc-0.2.0.dist-info/WHEEL
agbpycc-0.2.0.dist-info/entry_points.txt
agbpycc-0.2.0.dist-info/top_level.txt
agbpycc-0.2.0.dist-info/RECORD
