Metadata-Version: 2.1
Name: agbpycc
Version: 0.2.0
Summary: agbcc python frontend
Home-page: https://gitlab.com/henny022/agbpycc
Author: Henny022
Author-email: hen.geheim22@gmail.com
License: Unlicense
Platform: UNKNOWN
Classifier: License :: OSI Approved :: The Unlicense (Unlicense)
Classifier: Programming Language :: Python :: 3
Classifier: Programming Language :: Python :: 3.7
Requires-Python: >=3.7
Requires-Dist: antlr4-python3-runtime (==4.9.2)
